__init__.py
monitoring_service/__init__.py
monitoring_service/api.py
monitoring_service/cli.py
monitoring_service/constants.py
monitoring_service/database.py
monitoring_service/events.py
monitoring_service/exceptions.py
monitoring_service/handlers.py
monitoring_service/metrics.py
monitoring_service/schema.sql
monitoring_service/service.py
monitoring_service/states.py
pathfinding_service/__init__.py
pathfinding_service/api.py
pathfinding_service/claim_fees.py
pathfinding_service/cli.py
pathfinding_service/constants.py
pathfinding_service/database.py
pathfinding_service/exceptions.py
pathfinding_service/metrics.py
pathfinding_service/middleware.py
pathfinding_service/schema.sql
pathfinding_service/service.py
pathfinding_service/typing.py
pathfinding_service/model/__init__.py
pathfinding_service/model/channel.py
pathfinding_service/model/feedback.py
pathfinding_service/model/iou.py
pathfinding_service/model/token_network.py
raiden_libs/__init__.py
raiden_libs/api.py
raiden_libs/blockchain.py
raiden_libs/cli.py
raiden_libs/constants.py
raiden_libs/contract_info.py
raiden_libs/database.py
raiden_libs/events.py
raiden_libs/exceptions.py
raiden_libs/logging.py
raiden_libs/marshmallow.py
raiden_libs/matrix.py
raiden_libs/metrics.py
raiden_libs/service_registry.py
raiden_libs/states.py
raiden_libs/tracing.py
raiden_libs/user_address.py
raiden_libs/utils.py
request_collector/__init__.py
request_collector/cli.py
request_collector/server.py
raiden_services-2.0.1.dist-info/LICENSE
raiden_services-2.0.1.dist-info/METADATA
raiden_services-2.0.1.dist-info/WHEEL
raiden_services-2.0.1.dist-info/entry_points.txt
raiden_services-2.0.1.dist-info/top_level.txt
raiden_services-2.0.1.dist-info/RECORD
