Metadata-Version: 2.1
Name: raiden-services
Version: 2.0.1
Summary: Raiden Services contain additional tools for the Raiden Network.
Home-page: https://github.com/raiden-network/raiden-services
Author: Brainbot Labs Est.
Author-email: contact@brainbot.li
License: MIT
Keywords: raiden,ethereum,blockchain
Platform: UNKNOWN
Classifier: Development Status :: 4 - Beta
Classifier: Intended Audience :: Developers
Classifier: License :: OSI Approved :: MIT License
Classifier: Natural Language :: English
Classifier: Programming Language :: Python :: 3
Classifier: Programming Language :: Python :: 3.8
Classifier: Programming Language :: Python :: 3.9
License-File: LICENSE
Requires-Dist: raiden
Requires-Dist: sentry-sdk[flask] (==1.5.10)
Requires-Dist: prometheus-client (==0.14.1)
Requires-Dist: networkx (==2.8)
Requires-Dist: jaeger-client (==4.8.0)
Requires-Dist: dbapi-opentracing (==0.0.5)
Requires-Dist: Flask-Opentracing (==1.1.0)
Requires-Dist: requests-opentracing (==0.3.0)
Provides-Extra: dev
Requires-Dist: wheel (>=0.30.0) ; extra == 'dev'
Requires-Dist: watchdog (>=0.8.3) ; extra == 'dev'
Requires-Dist: flake8 (==3.9.2) ; extra == 'dev'
Requires-Dist: flake8-bugbear (==22.4.25) ; extra == 'dev'
Requires-Dist: flake8-tuple (==0.4.1) ; extra == 'dev'
Requires-Dist: isort (==5.10.1) ; extra == 'dev'
Requires-Dist: mypy (==0.950) ; extra == 'dev'
Requires-Dist: black (==22.3.0) ; extra == 'dev'
Requires-Dist: pylint (==2.13.7) ; extra == 'dev'
Requires-Dist: pytest ; extra == 'dev'
Requires-Dist: pytest-gevent ; extra == 'dev'
Requires-Dist: pytest-runner ; extra == 'dev'
Requires-Dist: pytest-cov ; extra == 'dev'
Requires-Dist: pytest-structlog (==0.5) ; extra == 'dev'
Requires-Dist: pytest-xdist ; extra == 'dev'
Requires-Dist: coverage (>=4.5.4) ; extra == 'dev'
Requires-Dist: ipython (==8.2.0) ; extra == 'dev'
Requires-Dist: pdbpp ; extra == 'dev'
Requires-Dist: eth-tester[py-evm] (==0.6.0b6) ; extra == 'dev'
Requires-Dist: bump2version ; extra == 'dev'
Requires-Dist: twine ; extra == 'dev'
Requires-Dist: types-setuptools ; extra == 'dev'
Requires-Dist: types-requests ; extra == 'dev'
